patchguard/__init__.py
patchguard/app/__init__.py
patchguard-0.0.1.dist-info/entry_points.txt
patchguard-0.0.1.dist-info/LICENSE
patchguard-0.0.1.dist-info/WHEEL
patchguard-0.0.1.dist-info/METADATA
patchguard-0.0.1.dist-info/RECORD
